{
  "main": {
    "id": "61f210a3e75bc5fb",
    "type": "split",
    "children": [
      {
        "id": "2ed068fdce0ba861",
        "type": "tabs",
        "children": [
          {
            "id": "09f092482881596f",
            "type": "leaf",
            "state": {
              "type": "empty",
              "state": {}
            }
          }
        ]
      }
    ],
    "direction": "vertical"
  },
  "left": {
    "id": "9de9ace4f25fb458",
    "type": "split",
    "children": [
      {
        "id": "631fd72ade8ce58d",
        "type": "tabs",
        "children": [
          {
            "id": "acfa305c99aa7427",
            "type": "leaf",
            "state": {
              "type": "file-explorer",
              "state": {
                "sortOrder": "alphabetical"
              }
            }
          },
          {
            "id": "9086fba33c94ae1b",
            "type": "leaf",
            "state": {
              "type": "search",
              "state": {
                "query": "",
                "matchingCase": false,
                "explainSearch": false,
                "collapseAll": false,
                "extraContext": false,
                "sortOrder": "alphabetical"
              }
            }
          },
          {
            "id": "c2212a50ed69311f",
            "type": "leaf",
            "state": {
              "type": "bookmarks",
              "state": {}
            }
          }
        ]
      },
      {
        "id": "a14c5693f5463fc1",
        "type": "tabs",
        "children": [
          {
            "id": "e3f77537e0ebace8",
            "type": "leaf",
            "state": {
              "type": "outline",
              "state": {}
            }
          }
        ]
      }
    ],
    "direction": "horizontal",
    "width": 300
  },
  "right": {
    "id": "bbad5c880586bc53",
    "type": "split",
    "children": [
      {
        "id": "413c01d99c7ceb6f",
        "type": "tabs",
        "dimension": 29.385964912280706,
        "children": [
          {
            "id": "d88819423420f4ac",
            "type": "leaf",
            "state": {
              "type": "all-properties",
              "state": {
                "sortOrder": "frequency",
                "showSearch": false,
                "searchQuery": ""
              }
            }
          },
          {
            "id": "2379b75c2ed6f65f",
            "type": "leaf",
            "state": {
              "type": "Strange New Worlds",
              "state": {}
            }
          },
          {
            "id": "970c0ebe784733ad",
            "type": "leaf",
            "state": {
              "type": "tag",
              "state": {
                "sortOrder": "frequency",
                "useHierarchy": true
              }
            }
          }
        ],
        "currentTab": 1
      },
      {
        "id": "b2e398d710777b6e",
        "type": "tabs",
        "dimension": 70.6140350877193,
        "children": [
          {
            "id": "981b75af9e493464",
            "type": "leaf",
            "state": {
              "type": "backlink",
              "state": {
                "collapseAll": false,
                "extraContext": false,
                "sortOrder": "alphabetical",
                "showSearch": false,
                "searchQuery": "",
                "backlinkCollapsed": false,
                "unlinkedCollapsed": false
              }
            }
          },
          {
            "id": "a94b1fa819925d9c",
            "type": "leaf",
            "state": {
              "type": "outgoing-link",
              "state": {
                "linksCollapsed": false,
                "unlinkedCollapsed": true
              }
            }
          }
        ]
      }
    ],
    "direction": "horizontal",
    "width": 300,
    "collapsed": true
  },
  "left-ribbon": {
    "hiddenItems": {
      "quartz-syncer:Quartz Syncer Publication Center": false,
      "switcher:Open quick switcher": true,
      "templates:Insert template": true,
      "graph:Open graph view": false,
      "command-palette:Open command palette": true,
      "markdown-importer:Open format converter": true,
      "cmdr:QuickAdd: New Subject": false,
      "omnisearch:Omnisearch": false,
      "obsidian42-brat:BRAT": false
    }
  },
  "active": "09f092482881596f",
  "lastOpenFiles": [
    "2024/Semester 1/MATH2400/Week 3/Lecture 1 - Monotone Convergence Theorem.md",
    "2024/Definitions/Integral Test.md",
    "2024/Semester 1/MATH2400/Week 3",
    "2024/Semester 1/CSSE2010/Week 2/Lecture 1 - Binary Arithmetic.md",
    "2024/Semester 1/CSSE2010/Week 1/Lab 1 - Number Representations.md",
    "Attachment Folder/Pasted image 20240229144325.png",
    "Attachment Folder/Pasted image 20240229144028.png",
    "2024/Semester 1/CSSE2010/Week 1/Lecture 2 - Introduction to Logic Gates.md",
    "Attachment Folder/Pasted image 20240229142125.png",
    "Attachment Folder/Pasted image 20240229141420.png",
    "Attachment Folder/Pasted image 20240229141237.png",
    "Attachment Folder/Pasted image 20240229135015.png",
    "Attachment Folder/Pasted image 20240229134952.png",
    "Attachment Folder/Pasted image 20240229134938.png",
    "2024/Definitions/Logic Gates.md",
    "2024/Semester 1/CSSE2010/Week 1/Lecture 1 - Course Intro and Binary Numbers.md",
    "2024/Semester 1/ELEC2400/Week 2/Lecture 1 - PN Junctions and Diode Circuits.md",
    "2024/Semester 1/ELEC2400/Week 1/Lecture 1 & 2 - Course Introduction.md",
    "2024/Semester 1/ELEC2300/Week 1/Lecture 1.6 - Conductors in Electrostatic Equilibrium.md",
    "2024/Semester 1/ELEC2300/Week 1/Lecture 2.1 - Electric Dipoles.md",
    "2024/Semester 1/ELEC2300/Week 1/Lecture 2.2 - Parallel-Plate Capacitors.md",
    "2024/Semester 1/ELEC2300/Week 1/Lecture 1.2 - Electric Fields.md",
    "Random Stuff/Templates/Definitions.md",
    "Random Stuff/Templates/Lecture.md",
    "Random Stuff/Templates/Subject.md",
    "Random Stuff/Templates/Tutorial.md",
    "Random Stuff/Templates/Workshop.md",
    "2024/Semester 1/ELEC2300/Week 1/Lecture 1.5 - Gauss's Law.md",
    "2024/Semester 1/ELEC2300/Week 1/Lecture 1.4 - Field and Potential.md",
    "2024/Semester 1/ELEC2300/Week 1/Lecture 1.3 - Electric Potential.md",
    "2024/Semester 1/ELEC2300/Week 1/Lecture 1.1 - Columbs Law.md",
    "orphaned files output.md",
    "2024/Summer Semester/MATH1052/Chapter 1/New thing.md",
    "2024/Summer Semester/MATH1052/fun.md",
    "Definitions/null.md",
    "Attachment Folder/VFPt_dipole_animation_electric.gif",
    "Attachment Folder/Pasted image 20240227103113.png",
    "2024/Semester 1/ELEC2400/Week 2",
    "2024/Semester 1/ELEC2300/Week 1",
    "2024/Semester 1/MATH2400/Week 2",
    "2024/Semester 1/CSSE2010/Week 2",
    "2024/Semester 1/ELEC2300",
    "2024/Semester 1/elec2300",
    "2024/Semester 1/ELEC2400/Week 1",
    "2024/Semester 1/ELEC2400",
    "2024/Semester 1/MATH2400/Week 1"
  ]
}