{
  "pythonPath": "python3",
  "cacheDirPath": "C:\\Users\\jamie\\AppData\\Local\\Obsidian\\.obsidian\\plugins\\latex-ocr\\model_cache",
  "delimiters": "$$",
  "port": "50051",
  "startServerOnLoad": true,
  "showStatusBar": true,
  "useLocalModel": false,
  "hfApiKey": {
    "type": "Buffer",
    "data": [
      118,
      49,
      48,
      6,
      76,
      165,
      229,
      243,
      100,
      104,
      38,
      90,
      136,
      198,
      85,
      216,
      13,
      13,
      73,
      61,
      12,
      71,
      193,
      229,
      167,
      183,
      199,
      42,
      144,
      35,
      154,
      140,
      46,
      164,
      44,
      191,
      1,
      100,
      94,
      219,
      69,
      232,
      184,
      250,
      192,
      127,
      216,
      156,
      12,
      106,
      82,
      246,
      204,
      247,
      20,
      172,
      78,
      73,
      132,
      117,
      170,
      207,
      54,
      66,
      236,
      115,
      74,
      20
    ]
  },
  "obfuscatedKey": "hf_****XRYl"
}